README.md
setup.py
FCM/CommonCollection.py
FCM/MCCollection.py
FCM/MCCore.py
FCM/MCServers.py
FCM/__init__.py
FCM/FQ/__init__.py
FCM/Jarticle/__init__.py
FCM/Jarticle/jArticles.py
FCM/Jarticle/jCompany.py
FCM/Jarticle/jCryptocurrencies.py
FCM/Jarticle/jModels.py
FCM/Jarticle/jSources.py
FCM/Jarticle/jVirtualWorld.py
FCM/Jarticle/jProvider/__init__.py
FCM/Jarticle/jProvider/jCategories.py
FCM/Jarticle/jProvider/jDate.py
FCM/Jarticle/jProvider/jSearch.py
FCM/Jarticle/jProvider/jSocial.py
FCM/Jarticle/jProvider/jSort.py
FCM/Jarticle/jdexes/__init__.py
FCM/Jarticle/jdexes/jArchive.py
FCM/Jarticle/jdexes/jNLP.py
FCM/Jarticle/jdexes/jURL.py
FCM/Jarticle/jdexes/jWords.py
FM/FMC.py
FM/FMClient.py
FM/FMDb.py
FM/FMRecord.py
FM/PipelineHelper.py
FM/QueryHelper.py
FM/__init__.py
FairMongo.egg-info/PKG-INFO
FairMongo.egg-info/SOURCES.txt
FairMongo.egg-info/dependency_links.txt
FairMongo.egg-info/requires.txt
FairMongo.egg-info/top_level.txt
pyFongo/CollectionEngine.py
pyFongo/CommandEngine.py
pyFongo/SearchArticles.py
pyFongo/UserRequest.py
pyFongo/__init__.py
pyFongo/main.py