Metadata-Version: 2.1
Name: FairMongo
Version: 5.1.0
Summary: A complete Python Package for PyMongo and MongoDB.
Home-page: https://github.com/chazzcoin/FairMongo
Author: ChazzCoin
Author-email: chazzcoin@gmail.com
License: BSD 2-clause
Platform: UNKNOWN
Classifier: Development Status :: 1 - Planning
Classifier: Intended Audience :: Science/Research
Classifier: License :: OSI Approved :: BSD License
Classifier: Operating System :: POSIX :: Linux
Classifier: Programming Language :: Python :: 3.8
Classifier: Programming Language :: Python :: 3.9
